lodis/__init__.py
lodis/asyncio.py
lodis/base.py
lodis/constants.py
lodis/core.py
lodis/lists.py
lodis/management.py
lodis/sets.py
lodis/sorted_sets.py
lodis/strings.py
lodis-1.1.0.dist-info/METADATA
lodis-1.1.0.dist-info/WHEEL
lodis-1.1.0.dist-info/licenses/LICENSE
lodis-1.1.0.dist-info/RECORD
