Metadata-Version: 2.4
Name: lodis
Version: 1.1.0
Summary: A lightweight, in-memory key-value store with TTL (time-to-live) expiration
Project-URL: Homepage, https://github.com/josenk/lodis
Project-URL: Repository, https://github.com/josenk/lodis.git
Project-URL: Issues, https://github.com/josenk/lodis/issues
Author-email: Jonathan Senkerik <jsenkerik@proton.me>
Maintainer-email: Jonathan Senkerik <jsenkerik@proton.me>
License: MIT License
License-File: LICENSE
Keywords: cache,in-memory,key-value,redis-like,ttl
Classifier: Development Status :: 5 - Production/Stable
Classifier: Intended Audience :: Developers
Classifier: License :: OSI Approved :: MIT License
Classifier: Operating System :: OS Independent
Classifier: Programming Language :: Python :: 3
Classifier: Programming Language :: Python :: 3.7
Classifier: Programming Language :: Python :: 3.8
Classifier: Programming Language :: Python :: 3.9
Classifier: Programming Language :: Python :: 3.10
Classifier: Programming Language :: Python :: 3.11
Classifier: Programming Language :: Python :: 3.12
Classifier: Topic :: Database
Classifier: Topic :: Software Development :: Libraries :: Python Modules
Classifier: Topic :: System :: Distributed Computing
Requires-Python: >=3.7
Provides-Extra: dev
Requires-Dist: black; extra == 'dev'
Requires-Dist: build; extra == 'dev'
Requires-Dist: flake8; extra == 'dev'
Requires-Dist: mypy; extra == 'dev'
Requires-Dist: pytest-cov; extra == 'dev'
Requires-Dist: pytest>=6.0; extra == 'dev'
Requires-Dist: twine; extra == 'dev'
